{"breadcrumbs":[{"api_query":"/classifieds/v2/ads","label":"Alla","search_parameters":""},{"api_query":"/classifieds/v2/ads?cg=1000","label":"Fordon","search_parameters":"cg=1000"},{"api_query":"/classifieds/v2/ads?cg=1020","label":"Bilar","search_parameters":"cg=1020"},{"api_query":"/classifieds/v2/ads?cb=1\u0026cg=1020","label":"Alfa Romeo","search_parameters":"cb=1\u0026cg=1020"},{"api_query":"/classifieds/v2/ads?cb=1\u0026cbl1=0\u0026cg=1020","label":"Övriga","search_parameters":"cb=1\u0026cbl1=0\u0026cg=1020"},{"label":"Alfa Romeo Montreal * OBS: 5560 MIL *"}],"data":{"ad_id":"1001244590","ad_status":"active","advertiser":{"contact_methods":{"phone":true},"name":"Auto Classica of Sweden AB","store_name":"Auto Classica of Sweden AB","type":"store"},"body":"Ring för info samt prisuppgift!","category":[{"id":"1000","name":"Fordon"},{"id":"1020","name":"Bilar"}],"images":[{"height":480,"type":"image","url":"https://i.blocketcdn.se/pictures/asl/1001244590/3312377270.jpg","width":640},{"height":480,"type":"image","url":"https://i.blocketcdn.se/pictures/asl/1001244590/2075870093.jpg","width":640},{"height":480,"type":"image","url":"https://i.blocketcdn.se/pictures/asl/1001244590/3243143587.jpg","width":640},{"height":480,"type":"image","url":"https://i.blocketcdn.se/pictures/asl/1001244590/3053875747.jpg","width":640},{"height":480,"type":"image","url":"https://i.blocketcdn.se/pictures/asl/1001244590/3978578321.jpg","width":640},{"height":480,"type":"image","url":"https://i.blocketcdn.se/pictures/asl/1001244590/3268815462.jpg","width":640}],"latitude":55.446353378458205,"license_plate":"QQK164","list_id":"1001244590","list_time":"2024-04-10T13:40:09+02:00","location":[{"id":"23","name":"Skåne","query_key":"r"},{"id":"286","name":"Ystad","query_key":"m"}],"longitude":13.841781001815065,"map_url":"https://www.hitta.se/kartan/partner/blocketv2?ad_id=1001244590","parameter_groups":[{"label":"Allmän information","parameters":[{"id":"fuel","label":"Bränsle","value":"Bensin"},{"id":"gearbox","label":"Växellåda","value":"Manuell"},{"id":"mileage","label":"Miltal","value":"5 560"},{"id":"regdate","label":"Modellår","value":"1972"},{"id":"search_regdate","label":"Tillverkad","value":"1972"}],"type":"general"},{"label":"Information från BytBil","parameters":[{"id":"cx_make","label":"Märke","value":"Alfa Romeo"},{"id":"cx_engine_power","label":"Hästkrafter","suffix":"Hk","value":"194"},{"id":"cx_model","label":"Modell","value":"Montreal"},{"id":"car_chassis_type","label":"Biltyp","value":"Coupé"},{"id":"car_brand","label":"Tillverkare","value":"Alfa Romeo"},{"id":"level_1","label":"Modellfamilj","value":"Övriga"}],"type":"car"}],"partner_info":{"external_id":"17643019","name":"bytbil"},"price":{"suffix":"kr","value":1},"saved":false,"share_url":"https://www.blocket.se/annons/skane/alfa_romeo_montreal_obs_5560_mil_/1001244590","state_id":"13","store":{"address":"Mässingsgatan 3","blocket_url":"https://www.blocket.se/butik/autoclassicaofsweden","city":"Ystad","full_address":"Mässingsgatan 3\n27139 Ystad","image":{"height":186,"type":"image","url":"https://i.blocketcdn.se/static/2/store_presentation/stores/extra_13284_bxo.jpg","width":465},"logo":{"height":48,"type":"logo","url":"https://i.blocketcdn.se/pictures/stores/logo_13284_ebm.jpg","width":228},"name":"Auto Classica of Sweden AB","organisation_info":"Org.nr 556645-6587 (Bolagsverket)","phone":{"phone_number":"0411-66666","phone_number_itu":"+4641166666"},"store_id":"13284","store_type":"bas","subject":"Märkesoberoende handlare","url":"http://www.autoclassica.com","url_path":"autoclassicaofsweden","zipcode":"27139"},"subject":"Alfa Romeo Montreal * OBS: 5560 MIL *","type":"s","blocket_package":{"activated_providers":[],"ad_id":"1001244590","blocket_payment_backwards_compatability":null,"buyers_protection_fee":null,"eligible_providers":[],"fail_code":null,"failure":null,"feature_swish":true,"features":{"is_part_of_merge":true},"is_in_dispute":false,"partner":"other","payment_methods":[],"payment_request_entrance":null,"payment_url":null,"service_data":null,"shipping_buy_now_entrance":null,"state":"ineligible","transaction_dates":null,"urls":{"seller_activate":"https://www.blocket.se/frakt/saljare-aktiverar-start?ad_id=1001244590\u0026source=ai"}},"saved_count":93},"inventory":{"context":{"gam":{"api_keywords":{"adid":["1001244590"],"adtitle":["./Alfa%20Romeo%20Montreal%20%2A%20OBS:%205560%20MIL%20%2A"],"adtype":["s_c"],"appmode":["notinapp"],"blocket_section":["1000","1020"],"body_type":["6"],"brand":["alfa romeo"],"companyad":["1"],"country":["sverige"],"country_code":["se"],"county":["23"],"dealerhasownfinance":["0"],"fueltype":["bensin"],"gearbox":["manuell"],"id":["1001244590"],"itemimage":["https://i.blocketcdn.se/pictures/asl/1001244590/3312377270.jpg"],"itemsecuredthumb":["https://i.blocketcdn.se/pictures/asl/1001244590/3312377270.jpg"],"itemthumb":["https://i.blocketcdn.se/pictures/asl/1001244590/3312377270.jpg"],"lkf":["1286"],"market":["cars_used"],"mileage":["5 560"],"model":["ovriga"],"modelyear":["1972"],"municipality":["286"],"nmp_vertical":["mobility"],"page":["object"],"price":["1"],"price_range_4":["0-50000"],"publisher":["blocket"],"services":[],"storeid":["13284"],"subvertical":["cars"],"type":["16"],"vertical":["mobility"]},"client_keywords":{"cmp_advertising":"cmp_advertising","logged_in":"loggedin","page_gen":"pagegen","ppid_1":"schuserhash","ppid_2":"schenvhash","screen_height":"screenheight","screen_width":"screenwidth","site_mode":"sitemode","supply_type":"supply_type","viewport_height":"viewportheight","viewport_width":"viewportwidth"},"network_id":"23166775775"}},"placements":[{"gam":{"keywords":{"adformat":["wallpaper","toppanorama_wde"],"adsize":["980x240","1600x900","2x1"]},"media_types":[{"height":240,"type":"display","width":980},{"height":240,"type":"display","width":970},{"height":900,"type":"display","width":1600},{"type":"native"}],"path":"23166775775/blocket-mobility/wde/cars/object/top_1","target_id":"placement_panorama"},"type":"banner","vendor":"gam","viewport":"large"},{"gam":{"keywords":{"adformat":["post_it_1"],"adsize":["250x360","250x480","2x1"]},"media_types":[{"height":360,"type":"display","width":250},{"height":480,"type":"display","width":250},{"type":"native"}],"path":"23166775775/blocket-mobility/wde/cars/object/postit_1","target_id":"placement_widescreen-1"},"type":"banner","vendor":"gam","viewport":"large"},{"gam":{"keywords":{"adformat":["post_it_2"],"adsize":["250x360","250x480","2x1"]},"media_types":[{"height":360,"type":"display","width":250},{"height":480,"type":"display","width":250},{"type":"native"}],"path":"23166775775/blocket-mobility/wde/cars/object/postit_2","target_id":"placement_widescreen-2"},"type":"banner","vendor":"gam","viewport":"large"},{"gam":{"keywords":{"adformat":["post_it_3"],"adsize":["250x360","250x480","2x1"]},"media_types":[{"height":360,"type":"display","width":250},{"height":480,"type":"display","width":250},{"type":"native"}],"path":"23166775775/blocket-mobility/wde/cars/object/postit_3","target_id":"placement_widescreen-3"},"type":"banner","vendor":"gam","viewport":"large"},{"gam":{"keywords":{"adformat":["post_it_4"],"adsize":["250x360","250x480","2x1"]},"media_types":[{"height":360,"type":"display","width":250},{"height":480,"type":"display","width":250},{"type":"native"}],"path":"23166775775/blocket-mobility/wde/cars/object/postit_4","target_id":"placement_widescreen-4"},"type":"banner","vendor":"gam","viewport":"large"},{"gam":{"keywords":{"adformat":["pricedisplay"],"adsize":["185x20","2x1","300x20"]},"media_types":[{"height":20,"type":"display","width":185},{"height":20,"type":"display","width":300},{"type":"native"}],"path":"23166775775/blocket-mobility/wde/cars/object/price","target_id":"placement_price"},"type":"banner","vendor":"gam","viewport":"large"},{"gam":{"keywords":{"adformat":["infor_kopet_1"],"adsize":["1x1"]},"media_types":[{"height":92,"type":"display","width":368},{"height":1,"type":"display","width":1},{"type":"native"}],"path":"23166775775/blocket-mobility/wph/cars/object/native_1","target_id":"infor_kopet_1"},"type":"infor_kopet","vendor":"gam","viewport":"small"},{"gam":{"keywords":{"adformat":["infor_kopet_2"],"adsize":["1x1"]},"media_types":[{"height":92,"type":"display","width":368},{"height":1,"type":"display","width":1},{"type":"native"}],"path":"23166775775/blocket-mobility/wph/cars/object/native_2","target_id":"infor_kopet_2"},"type":"infor_kopet","vendor":"gam","viewport":"small"},{"gam":{"keywords":{"adformat":["panorama_bottom"],"adsize":["320x320","2x1"]},"media_types":[{"height":320,"type":"display","width":320},{"type":"native"}],"path":"23166775775/blocket-mobility/wph/cars/object/bottom_1","target_id":"vi_panorama_bottom"},"type":"banner","vendor":"gam","viewport":"small"},{"gam":{"keywords":{"adformat":["karusell"],"adsize":["320x320","1x1"]},"media_types":[{"height":320,"type":"display","width":320},{"type":"native"}],"path":"23166775775/blocket-mobility/wph/cars/object/incarousel","target_id":"vi_image_integration"},"type":"banner","vendor":"gam","viewport":"small"},{"safe_purchase":{"body":"Ska du sälja eller köpa en bil? Vi hjälper dig med förberedelser, råd och tips för bästa möjliga bilaffär.","header":"Trygg affär","links":[{"label":"Läs Blockets tips för en trygg affär","type":"info","url":"https://www.blocket.se/tips-och-guider/bilguiden"}],"partners":[{"body":"","header":"Trygghet \u0026 säkerhet på Blocket","icon_png":"https://images.ctfassets.net/rvdf5xmxjruf/3HHLh42mIq5gH57G9BDrQV/6958286baedcdce18a75cc53d8e6b0c9/general_safetytip.png","icon_svg":"https://images.ctfassets.net/rvdf5xmxjruf/4SPOb3fBJbo3QxUmfln9V3/f035d38afc67752b897b025a6e3106d7/general_safetytip.svg","id":"safety tip","is_advertisement":false,"link":{"label":"Tips för en trygg bilaffär","url":"https://www.blocket.se/tips-och-guider/bilguiden/category/kopa-och-salja-bil"},"tracking_creative":"safety tip bilar","tracking_position":"safety tip"}]},"type":"safe_purchase","vendor":"blocket","viewport":"universal"}]}}
